fastapiwee/__init__.py
fastapiwee/pwpd.py
fastapiwee/crud/__init__.py
fastapiwee/crud/base.py
fastapiwee/crud/exceptions.py
fastapiwee/crud/views.py
fastapiwee/crud/viewsets.py
fastapiwee/tests/__init__.py
fastapiwee/tests/test_pwpd.py
FastAPIwee-0.0.8.dist-info/LICENSE
FastAPIwee-0.0.8.dist-info/METADATA
FastAPIwee-0.0.8.dist-info/WHEEL
FastAPIwee-0.0.8.dist-info/top_level.txt
FastAPIwee-0.0.8.dist-info/RECORD
