Metadata-Version: 2.1
Name: FastAPIwee
Version: 0.0.8
Summary: FastAPIwee - FastAPI + PeeWee = <3
Home-page: https://github.com/Ignisor/FastAPIwee
Author: German Gensetskyi
Author-email: Ignis2497@gmail.com
License: UNKNOWN
Project-URL: Documentation, https://fastapiwee.qqmber.wtf
Platform: UNKNOWN
Classifier: Programming Language :: Python :: 3
Classifier: Operating System :: OS Independent
Requires-Python: >=3.6
Requires-Dist: fastapi (==0.66.0)
Requires-Dist: pydantic (==1.8.2)
Requires-Dist: peewee (==3.14.4)
